npf_web_extension/__init__.py
npf_web_extension/app.py
npf_web_extension/template.html
npf_web_extension-0.6.4.dist-info/LICENSE
npf_web_extension-0.6.4.dist-info/METADATA
npf_web_extension-0.6.4.dist-info/WHEEL
npf_web_extension-0.6.4.dist-info/entry_points.txt
npf_web_extension-0.6.4.dist-info/top_level.txt
npf_web_extension-0.6.4.dist-info/RECORD
